vlense/__init__.py
vlense/constants/__init__.py
vlense/constants/messages.py
vlense/constants/patterns.py
vlense/constants/prompts.py
vlense/core/__init__.py
vlense/core/types.py
vlense/core/vlense.py
vlense/errors/__init__.py
vlense/errors/base.py
vlense/errors/exceptions.py
vlense/lib/__init__.py
vlense/lib/image.py
vlense/lib/pdf.py
vlense/lib/text.py
vlense/models/__init__.py
vlense/models/litellmmodel.py
vlense/models/types.py
vlense/tests/__init__.py
vlense/tests/test_vlense.py
vlense-0.1.4.dist-info/LICENSE
vlense-0.1.4.dist-info/METADATA
vlense-0.1.4.dist-info/WHEEL
vlense-0.1.4.dist-info/top_level.txt
vlense-0.1.4.dist-info/RECORD
